helloworldextreme.py
helloworldextreme-0.0.1.dist-info/LICENSE.txt
helloworldextreme-0.0.1.dist-info/METADATA
helloworldextreme-0.0.1.dist-info/WHEEL
helloworldextreme-0.0.1.dist-info/top_level.txt
helloworldextreme-0.0.1.dist-info/RECORD
