Metadata-Version: 2.1
Name: helloworldextreme
Version: 0.0.1
Summary: The most universal piece of code. Ever.
Home-page: https://github.com/StoopidSam/HelloWorldExtreme
Author: StoopidSam
Author-email: firwoodmedia@gmail.com
License: UNKNOWN
Platform: UNKNOWN
Classifier: Programming Language :: Python :: 3
Classifier: Programming Language :: Python :: 3.6
Classifier: Programming Language :: Python :: 3.7
Classifier: License :: OSI Approved :: GNU General Public License v2 or later (GPLv2+)
Classifier: Operating System :: OS Independent
